{
  "Description": "write something here, please",
  "HomePage": "http://www.freedesktop.org",
  "BuilderName": "std_py23",
  "Removable": true,
  "Reducible": true,
  "NonInstallable": false,
  "Deprecated": true,
  "PrimaryInstallOnly": false,
  "BuildDeps": [
    ""
  ],
  "SODeps": [
    ""
  ],
  "RunTimeDeps": [
    ""
  ],
  "Tags": [
    "group:core0"
  ],
  "Category": "freedesktop/dbus",
  "Groups": [
    "core0"
  ],
  "TarballName": "dbus-python",
  "TarballFileNameParser": "std",
  "TarballFilters": [
    ""
  ],
  "TarballProvider": "https",
  "TarballProviderArguments": [
    "https://dbus.freedesktop.org/releases/"
  ],
  "TarballProviderUseCache": false,
  "TarballProviderCachePresetName": "",
  "TarballProviderVersionSyncDepth": 0,
  "TarballVersionTool": "std"
}
