{
  "Description": "",
  "HomePage": "https://sourceforge.net/projects/ogl-math",
  "BuilderName": "std_cmake",
  "Removable": true,
  "Reducible": true,
  "NonInstallable": false,
  "Deprecated": false,
  "PrimaryInstallOnly": false,
  "BuildDeps": [
    ""
  ],
  "SODeps": [
    ""
  ],
  "RunTimeDeps": [
    ""
  ],
  "Tags": [
    "sf_hosted:ogl-math"
  ],
  "Category": "non_categorized",
  "Groups": [
    "gl"
  ],
  "TarballFileNameParser": "std",
  "TarballName": "glm",
  "TarballFilters": [
    ""
  ],
  "TarballProvider": "sf.net",
  "TarballProviderArguments": [
    "ogl-math"
  ],
  "TarballProviderVersionSyncDepth": 0,
  "TarballStabilityClassifier": "std",
  "TarballVersionComparator": "std"
}
