{
  "Description": "write something here, please",
  "HomePage": "http://None",
  "BuilderName": "nspr",
  "Removable": true,
  "Reducible": true,
  "AutoReduce": true,
  "NonBuildable": false,
  "NonInstallable": false,
  "Deprecated": false,
  "PrimaryInstallOnly": false,
  "BuildPkgDeps": [],
  "BuildDeps": [],
  "SODeps": [],
  "RunTimeDeps": [],
  "Tags": [],
  "Category": "non_categorized",
  "Groups": [
    "web"
  ],
  "TarballFileNameParser": "std",
  "TarballName": "nspr",
  "TarballFilters": [],
  "TarballProvider": "",
  "TarballProviderArguments": [],
  "TarballProviderVersionSyncDepth": 0,
  "TarballStabilityClassifier": "std",
  "TarballVersionComparator": "std",
  "DownloadPatches": false,
  "PatchesDownloadingScriptText": ""
}
