{
  "Description": "",
  "HomePage": "",
  "BuilderName": "std",
  "Removable": true,
  "Reducible": true,
  "NonInstallable": false,
  "Deprecated": false,
  "PrimaryInstallOnly": false,
  "BuildDeps": [
    ""
  ],
  "SODeps": [
    ""
  ],
  "RunTimeDeps": [
    ""
  ],
  "Tags": [
    ""
  ],
  "Category": "freedesktop/pavucontrol",
  "Groups": [
    ""
  ],
  "TarballName": "pavucontrol",
  "TarballFileNameParser": "std",
  "TarballFilters": [
    ""
  ],
  "TarballProvider": "",
  "TarballProviderArguments": [
    ""
  ],
  "TarballProviderUseCache": false,
  "TarballProviderCachePresetName": "",
  "TarballProviderVersionSyncDepth": 0,
  "TarballVersionTool": "std"
}
