{
  "Description": "",
  "HomePage": "https://github.com/SRombauts/SQLiteCpp",
  "BuilderName": "std_cmake",
  "Removable": true,
  "Reducible": true,
  "AutoReduce": true,
  "NonInstallable": false,
  "Deprecated": false,
  "PrimaryInstallOnly": false,
  "BuildPkgDeps": [],
  "BuildDeps": [],
  "SODeps": [],
  "RunTimeDeps": [],
  "Tags": [
    "github_hosted"
  ],
  "Category": "non_categorized",
  "Groups": [],
  "TarballFileNameParser": "std",
  "TarballName": "sqlitecpp",
  "TarballFilters": [],
  "TarballProvider": "srs",
  "TarballProviderArguments": [
    "git",
    "https://github.com/SRombauts/SQLiteCpp.git",
    "sqlitecpp",
    "TagName:^$",
    "TagStatus:"
  ],
  "TarballProviderVersionSyncDepth": 3,
  "TarballStabilityClassifier": "std",
  "TarballVersionComparator": "std",
  "DownloadPatches": false,
  "PatchesDownloadingScriptText": ""
}
